rammon/__init__.py
rammon/__main__.py
rammon/commands.py
rammon/config.py
rammon/logging.py
rammon/rammon.py
rammon/signals.py
rammon/systemd.py
rammon-0.2.5.post2.dist-info/LICENSE
rammon-0.2.5.post2.dist-info/METADATA
rammon-0.2.5.post2.dist-info/WHEEL
rammon-0.2.5.post2.dist-info/entry_points.txt
rammon-0.2.5.post2.dist-info/top_level.txt
rammon-0.2.5.post2.dist-info/RECORD
