Metadata-Version: 2.1
Name: rammon
Version: 0.2.5.post2
Summary: A low-memory alert daemon
Home-page: https://github.com/jackadamson/rammon
Author: Jack Adamson
Author-email: jack@mrfluffybunny.com
License: UNKNOWN
Platform: UNKNOWN
Classifier: Programming Language :: Python :: 3
Classifier: License :: OSI Approved :: MIT License
Classifier: Operating System :: POSIX :: Linux
Requires-Python: >=3.6
Requires-Dist: pydbus
Requires-Dist: python-daemon
Requires-Dist: psutil
Requires-Dist: dataclasses
